squads/__init__.py
squads/admin.py
squads/app_settings.py
squads/apps.py
squads/auth_hooks.py
squads/decorators.py
squads/errors.py
squads/forms.py
squads/hooks.py
squads/managers.py
squads/providers.py
squads/signals.py
squads/tasks.py
squads/urls.py
squads/api/__init__.py
squads/api/schema.py
squads/api/groups/__init__.py
squads/api/groups/manage.py
squads/migrations/0001_initial.py
squads/migrations/0002_rename_require_approval_groups_req_approve_and_more.py
squads/migrations/__init__.py
squads/models/__init__.py
squads/models/filters.py
squads/models/general.py
squads/models/groups.py
squads/models/member.py
squads/static/squads/css/themes/default.min.css
squads/static/squads/css/themes/defaultdark.min.css
squads/static/squads/css/themes/famfamfam.png
squads/static/squads/css/themes/modern.min.css
squads/static/squads/css/themes/office-toolbar.min.css
squads/static/squads/css/themes/office.min.css
squads/static/squads/css/themes/square.min.css
squads/static/squads/css/themes/content/default.min.css
squads/static/squads/groups_images/empty.png
squads/static/squads/js/manage_groups.js
squads/static/squads/js/sceditor.min.js
squads/static/squads/js/formats/bbcode.js
squads/static/squads/js/formats/xhtml.js
squads/static/squads/js/icons/material.js
squads/static/squads/js/icons/monocons.js
squads/templates/squads/base.html
squads/templates/squads/index.html
squads/templates/squads/menu.html
squads/templates/squads/groups/browse_groups.html
squads/templates/squads/groups/membership_groups.html
squads/templates/squads/groups/pending_groups.html
squads/templates/squads/groups/view_group.html
squads/templates/squads/groups/partials/membership.html
squads/templates/squads/groups/partials/pending.html
squads/templates/squads/groups/partials/requirements.html
squads/templates/squads/manage/create_group.html
squads/templates/squads/manage/edit_group.html
squads/templates/squads/manage/manage_members.html
squads/templates/squads/manage/manage_pendings.html
aa_squads-0.2.4.1.dist-info/METADATA
aa_squads-0.2.4.1.dist-info/WHEEL
aa_squads-0.2.4.1.dist-info/licenses/LICENSE
aa_squads-0.2.4.1.dist-info/RECORD
